persona_generator/__init__.py
persona_generator/cli.py
persona_generator/exporters/persona_exporter.py
persona_generator/factories/persona_factory.py
persona_generator/generators/__init__.py
persona_generator/generators/base_generator.py
persona_generator/generators/openai.py
persona_generator/generators/config/config_loader.py
persona_generator/generators/config/generator_config.yaml
persona_generator/models/__init__.py
persona_generator/models/characteristics.py
persona_generator/models/persona.py
persona_generator/models/schema.py
persona_generator/schemas/characteristics.yaml
persona_generator/schemas/default_schema.yaml
persona_generator/schemas/example_schema.yaml
persona_generator/schemas/loader.py
persona_generator/schemas/validator.py
persona_generator-1.0.1.dist-info/licenses/LICENSE
persona_generator-1.0.1.dist-info/METADATA
persona_generator-1.0.1.dist-info/WHEEL
persona_generator-1.0.1.dist-info/entry_points.txt
persona_generator-1.0.1.dist-info/top_level.txt
persona_generator-1.0.1.dist-info/RECORD
