Metadata-Version: 2.4
Name: persona-generator
Version: 1.0.1
Summary: A powerful and flexible tool for generating detailed, consistent, and diverse personas using AI models
Author-email: Ciro Gamboa <ciro@example.com>
Maintainer-email: Ciro Gamboa <ciro@example.com>
License-Expression: MIT
Project-URL: Homepage, https://github.com/CiroGamboa/persona-generator
Project-URL: Repository, https://github.com/CiroGamboa/persona-generator
Project-URL: Issues, https://github.com/CiroGamboa/persona-generator/issues
Keywords: persona,ai,generation,openai,yaml,schema
Classifier: Development Status :: 4 - Beta
Classifier: Intended Audience :: Developers
Classifier: Operating System :: OS Independent
Classifier: Programming Language :: Python :: 3
Classifier: Programming Language :: Python :: 3.8
Classifier: Programming Language :: Python :: 3.9
Classifier: Programming Language :: Python :: 3.10
Classifier: Programming Language :: Python :: 3.11
Classifier: Programming Language :: Python :: 3.12
Classifier: Topic :: Software Development :: Libraries :: Python Modules
Classifier: Topic :: Scientific/Engineering :: Artificial Intelligence
Requires-Python: >=3.8
License-File: LICENSE
Requires-Dist: pyyaml>=6.0.0
Requires-Dist: openai>=1.0.0
Requires-Dist: python-dotenv>=1.0.0
Provides-Extra: dev
Requires-Dist: pytest>=7.0.0; extra == "dev"
Requires-Dist: black>=22.0.0; extra == "dev"
Requires-Dist: flake8>=4.0.0; extra == "dev"
Requires-Dist: mypy>=0.950; extra == "dev"
Provides-Extra: test
Requires-Dist: pytest>=7.0.0; extra == "test"
Requires-Dist: pytest-cov>=3.0.0; extra == "test"
Dynamic: license-file
